time_series_split/__init__.py
time_series_split/split_ts.py
time_series_split-0.1.8.dist-info/LICENSE
time_series_split-0.1.8.dist-info/METADATA
time_series_split-0.1.8.dist-info/WHEEL
time_series_split-0.1.8.dist-info/RECORD
